{
  "sections": {
    "image_banner": {
      "type": "image-banner",
      "blocks": {
        "heading": {
          "type": "heading",
          "settings": {
            "heading": "Ski poles you’ll <strong>actually<\/strong> want to brag about",
            "heading_size": "h1"
          }
        }
      },
      "block_order": [
        "heading"
      ],
      "settings": {
        "image": "shopify:\/\/shop_images\/Screenshot_2023-10-15_at_6.35.03_PM.png",
        "image_overlay_opacity": 0,
        "image_height": "medium",
        "desktop_content_position": "bottom-left",
        "show_text_box": false,
        "desktop_content_alignment": "left",
        "color_scheme": "inverse",
        "mobile_content_alignment": "left",
        "stack_images_on_mobile": false,
        "show_text_below": false
      }
    },
    "rich_text": {
      "type": "rich-text",
      "blocks": {
        "text": {
          "type": "text",
          "settings": {
            "text": "<p>At Yardsale, we believe you don’t have to be the most serious skier on the mountain to have a great day. You just need good people, great products, and some sunshine. <\/p>",
            "text_size": "medium"
          }
        },
        "dde367d0-110c-4d3c-81a3-e3b914edb281": {
          "type": "button",
          "settings": {
            "button_label": "Learn more →",
            "button_link": "",
            "button_style_secondary": false,
            "button_label_2": "",
            "button_link_2": "",
            "button_style_secondary_2": false
          }
        }
      },
      "block_order": [
        "text",
        "dde367d0-110c-4d3c-81a3-e3b914edb281"
      ],
      "settings": {
        "desktop_content_position": "center",
        "content_alignment": "left",
        "color_scheme": "background-1"
      }
    },
    "video": {
      "type": "video",
      "settings": {
        "heading": "",
        "heading_size": "h1",
        "enable_video_looping": true,
        "video": "shopify:\/\/files\/videos\/untitled (1080p).mp4",
        "video_url": "",
        "description": "",
        "full_width": false,
        "color_scheme": "inverse",
        "padding_top": 0,
        "padding_bottom": 0
      }
    },
    "742133b8-6152-4597-a606-78a079616c87": {
      "type": "multirow",
      "blocks": {
        "template--21549409567031__742133b8-6152-4597-a606-78a079616c87-row-1": {
          "type": "row",
          "settings": {
            "image": "shopify:\/\/shop_images\/ae26248bfd173cf9debbd247bddc92f5.jpg",
            "caption": "",
            "heading": "Magnetic poles",
            "text": "",
            "button_label": "",
            "button_link": ""
          }
        },
        "template--21549409567031__742133b8-6152-4597-a606-78a079616c87-row-2": {
          "type": "row",
          "settings": {
            "image": "shopify:\/\/shop_images\/60fb1476e2b478630ac34a28ae233cf7.jpg",
            "caption": "",
            "heading": "Straps that stay open",
            "text": "",
            "button_label": "",
            "button_link": ""
          }
        },
        "template--21549409567031__742133b8-6152-4597-a606-78a079616c87-row-3": {
          "type": "row",
          "settings": {
            "image": "shopify:\/\/shop_images\/6ca08e4c8f2da9449fef9d2ebad5e9dd.png",
            "caption": "",
            "heading": "GoPro® mount",
            "text": "",
            "button_label": "",
            "button_link": ""
          }
        },
        "b426a280-0b91-4e03-bf29-8ffd9ea228d1": {
          "type": "row",
          "settings": {
            "image": "shopify:\/\/shop_images\/e4c1eff08866d3ce5975f8c0f3c21c5b.jpg",
            "caption": "",
            "heading": "Mix-and-match colors",
            "text": "",
            "button_label": "",
            "button_link": ""
          }
        }
      },
      "block_order": [
        "template--21549409567031__742133b8-6152-4597-a606-78a079616c87-row-1",
        "template--21549409567031__742133b8-6152-4597-a606-78a079616c87-row-2",
        "template--21549409567031__742133b8-6152-4597-a606-78a079616c87-row-3",
        "b426a280-0b91-4e03-bf29-8ffd9ea228d1"
      ],
      "settings": {
        "image_height": "medium",
        "desktop_image_width": "medium",
        "heading_size": "h3",
        "text_style": "body",
        "button_style": "secondary",
        "desktop_content_position": "middle",
        "desktop_content_alignment": "left",
        "image_layout": "float-right",
        "section_color_scheme": "",
        "row_color_scheme": "",
        "mobile_content_alignment": "left"
      }
    },
    "cda9a249-bd53-4cc6-af49-81261315d9bd": {
      "type": "multicolumn",
      "blocks": {
        "template--21549409567031__cda9a249-bd53-4cc6-af49-81261315d9bd-column-1": {
          "type": "column",
          "settings": {
            "title": "",
            "text": "<h6>Sarah S., Los Angeles<\/h6><p>“These are UNREAL. Why has nobody thought of this before?” <\/p>",
            "link_label": "",
            "link": ""
          }
        },
        "template--21549409567031__cda9a249-bd53-4cc6-af49-81261315d9bd-column-2": {
          "type": "column",
          "settings": {
            "title": "",
            "text": "<h6>Manny G., New York City<\/h6><p>“Nothing about poles has ever been sexy until Yardsale.”<\/p>",
            "link_label": "",
            "link": ""
          }
        },
        "template--21549409567031__cda9a249-bd53-4cc6-af49-81261315d9bd-column-3": {
          "type": "column",
          "settings": {
            "title": "",
            "text": "<h6>Nick L., Seattle <\/h6><p>“I’m obsessed with the design. Perfect blend of technical, modern, but also classic.”<\/p>",
            "link_label": "",
            "link": ""
          }
        }
      },
      "block_order": [
        "template--21549409567031__cda9a249-bd53-4cc6-af49-81261315d9bd-column-1",
        "template--21549409567031__cda9a249-bd53-4cc6-af49-81261315d9bd-column-2",
        "template--21549409567031__cda9a249-bd53-4cc6-af49-81261315d9bd-column-3"
      ],
      "settings": {
        "title": "Skiers love Yardsale",
        "heading_size": "h2",
        "image_width": "full",
        "image_ratio": "adapt",
        "columns_desktop": 3,
        "column_alignment": "left",
        "background_style": "none",
        "button_label": "",
        "button_link": "",
        "color_scheme": "background-1",
        "columns_mobile": "1"
      }
    },
    "a5a48154-0536-49fa-846c-5fb78758f557": {
      "type": "image-with-text",
      "blocks": {
        "template--21549409567031__a5a48154-0536-49fa-846c-5fb78758f557-heading-1": {
          "type": "heading",
          "settings": {
            "heading": "Yardsale P1 Poles",
            "heading_size": "h2"
          }
        },
        "template--21549409567031__a5a48154-0536-49fa-846c-5fb78758f557-button-1": {
          "type": "button",
          "settings": {
            "button_label": "Customize your pole",
            "button_link": "shopify:\/\/collections\/p1-poles",
            "button_style_secondary": false
          }
        }
      },
      "block_order": [
        "template--21549409567031__a5a48154-0536-49fa-846c-5fb78758f557-heading-1",
        "template--21549409567031__a5a48154-0536-49fa-846c-5fb78758f557-button-1"
      ],
      "settings": {
        "image": "shopify:\/\/shop_images\/ec841c40ee621ff08d7b7aabb5ed2520-2.jpg",
        "height": "small",
        "desktop_image_width": "medium",
        "layout": "text_left",
        "desktop_content_position": "top",
        "desktop_content_alignment": "left",
        "color_scheme": "background-2",
        "image_behavior": "none",
        "mobile_content_alignment": "left",
        "padding_top": 36,
        "padding_bottom": 36
      }
    }
  },
  "order": [
    "image_banner",
    "rich_text",
    "video",
    "742133b8-6152-4597-a606-78a079616c87",
    "cda9a249-bd53-4cc6-af49-81261315d9bd",
    "a5a48154-0536-49fa-846c-5fb78758f557"
  ]
}